{
  "schema": "alberta-policy-rollout-diagnostic-v1",
  "checkpoint_dir": "evidence/local_learning_probe_hiwonder_low_slip_recovery_feedback_survives_taper_scale12_seed65_3k",
  "profile_id": "hiwonder-ainex",
  "task": "walk_forward",
  "episodes": [
    {
      "episode": 0,
      "summary": {
        "steps": 33,
        "terminated_reason": "support_contract",
        "goal_success": false,
        "goal_reason": "",
        "goal_success_window_s": 0.0,
        "final_tracked_delta_x_m": 0.14670032439548686,
        "final_tracked_delta_y_m": -0.0011824509797746371,
        "final_tracked_z_m": 0.2411353636533085,
        "final_delta_yaw_rad": -0.2881464592525926,
        "max_tracked_delta_x_m": 0.14670032439548686,
        "max_abs_delta_yaw_rad": 0.2881464592525926,
        "max_abs_pitch_rad": 0.1912752819412233,
        "max_abs_roll_rad": 0.2169653186705503,
        "max_foot_slip_m_s": 0.6797677278518677,
        "min_robot_geom_floor_clearance_m": -0.0016291755274510274,
        "floor_penetration_tolerance_m": 0.005,
        "below_floor_step_count": 0,
        "geometry_floor_ok": true,
        "foot_contact_switch_count": 2,
        "first_slip_limit_step": 32,
        "first_required_contacts_step": 33,
        "first_no_support_after_required_contacts_step": null,
        "first_near_fall_tilt_step": null,
        "reward_totals": {
          "action_rate": -0.0004350048203195912,
          "alive": 33.0,
          "alternating_contact": 0.0,
          "contact_cadence": 0.0,
          "double_support": -5.0,
          "drift": 0.0,
          "energy": -0.0013412341717630625,
          "foot_clearance": 0.0,
          "foot_slip": -2.674554687924683,
          "foot_spacing": 0.0,
          "gait_prior": 0.0,
          "goal_hold_brake": 0.0,
          "goal_hold_slip": 0.0,
          "goal_hold_support": 0.0,
          "height_track": 16.287522642913757,
          "late_hold_instability": 0.0,
          "late_hold_speed": 0.0,
          "movement_progress": 6.570575417851558,
          "no_progress": -131.7706973330893,
          "no_support": 0.0,
          "residual_energy": -0.034996479327674024,
          "residual_guard_suppression": -0.011208345531485975,
          "residual_tilt_guard": 0.0,
          "residual_yaw_guard": -1.0173044402132494e-05,
          "self_collision": 0.0,
          "stance_contact": 0.0,
          "support_contract": -13.190709114074707,
          "support_contract_after_progress": -39.12008650546316,
          "support_contract_remaining_horizon": -58.75,
          "support_contract_terminal_penalty": -100.0,
          "tilt_margin": 0.0,
          "upright": 32.76741425528511,
          "velocity_track": 0.29881777126846065,
          "yaw_drift_margin": -4.810315320360154,
          "yaw_track": 0.0
        }
      },
      "steps": [
        {
          "step": 1,
          "t_s": 0.02,
          "matched_task": "walk_forward",
          "reward": -4.527554221456076,
          "done_reason": null,
          "tracked_delta_x": 0.0001506210752892864,
          "tracked_delta_y": 3.624166447849495e-05,
          "tracked_z": 0.24059675791023533,
          "delta_yaw": -0.0016138887242293004,
          "imu_pitch": -0.003349689104215707,
          "imu_roll": -0.0002123961367043498,
          "left_foot_contact": true,
          "right_foot_contact": true,
          "foot_contact_switch_count": 0,
          "left_foot_slip_m_s": 0.003742748638615012,
          "right_foot_slip_m_s": 0.008852161467075348,
          "max_foot_slip_m_s": 0.008852161467075348,
          "min_robot_geom_floor_clearance_m": -0.0011313880438556037,
          "below_floor_robot_geom_count": 0,
          "worst_below_floor_robot_geom": "",
          "floor_penetration_tolerance_m": 0.005,
          "locomotion_prior_goal_hold_scale": 1.0,
          "locomotion_prior_residual_stability_scale": 1.0,
          "reward_terms": {
            "alive": 1.0,
            "height_track": 0.47645006252567196,
            "velocity_track": 0.005365257128916866,
            "yaw_track": 0.0,
            "contact_cadence": 0.0,
            "stance_contact": 0.0,
            "foot_clearance": 0.0,
            "no_support": -0.0,
            "double_support": -2.0,
            "foot_slip": -0.008852161467075348,
            "foot_spacing": -0.0,
            "self_collision": -0.0,
            "support_contract": -0.0,
            "upright": 0.9999943672407655,
            "movement_progress": 0.00020082810038571524,
            "alternating_contact": 0.0,
            "no_progress": -4.999372412186295,
            "gait_prior": 0.0,
            "action_rate": -0.00012298524379730224,
            "energy": -1.2298524379730225e-05,
            "residual_energy": -0.0011804605601355433,
            "residual_guard_suppression": -0.0,
            "residual_yaw_guard": -0.0,
            "residual_tilt_guard": -0.0,
            "tilt_margin": -0.0,
            "yaw_drift_margin": -2.4418470133073235e-05,
            "drift": -0.0,
            "late_hold_instability": -0.0,
            "late_hold_speed": -0.0,
            "goal_hold_brake": -0.0,
            "goal_hold_slip": -0.0,
            "goal_hold_support": 0.0
          }
        },
        {
          "step": 2,
          "t_s": 0.04,
          "matched_task": "walk_forward",
          "reward": -4.534840272435194,
          "done_reason": null,
          "tracked_delta_x": 0.00036720746786034317,
          "tracked_delta_y": 8.086079861046105e-05,
          "tracked_z": 0.24170113563554504,
          "delta_yaw": -0.0004080613728511094,
          "imu_pitch": -0.003271831924832287,
          "imu_roll": -0.0006604247633722696,
          "left_foot_contact": true,
          "right_foot_contact": true,
          "foot_contact_switch_count": 0,
          "left_foot_slip_m_s": 0.017183801159262657,
          "right_foot_slip_m_s": 0.024077851325273514,
          "max_foot_slip_m_s": 0.024077851325273514,
          "min_robot_geom_floor_clearance_m": -0.00044690204829165355,
          "below_floor_robot_geom_count": 0,
          "worst_below_floor_robot_geom": "",
          "floor_penetration_tolerance_m": 0.005,
          "locomotion_prior_goal_hold_scale": 1.0,
          "locomotion_prior_residual_stability_scale": 1.0,
          "reward_terms": {
            "alive": 1.0,
            "height_track": 0.481773311769353,
            "velocity_track": 0.006411242752564101,
            "yaw_track": 0.0,
            "contact_cadence": 0.0,
            "stance_contact": 0.0,
            "foot_clearance": 0.0,
            "no_support": -0.0,
            "double_support": -2.0,
            "foot_slip": -0.024077851325273514,
            "foot_spacing": -0.0,
            "self_collision": -0.0,
            "support_contract": -0.0,
            "upright": 0.9999944294834437,
            "movement_progress": 0.0004896099571471243,
            "alternating_contact": 0.0,
            "no_progress": -4.998469968883915,
            "gait_prior": 0.0,
            "action_rate": -1.4610112411901355e-05,
            "energy": -1.2536359019577503e-05,
            "residual_energy": -0.000932338647544384,
            "residual_guard_suppression": -0.0,
            "residual_yaw_guard": -0.0,
            "residual_tilt_guard": -0.0,
            "tilt_margin": -0.0,
            "yaw_drift_margin": -1.5610695376231133e-06,
            "drift": -0.0,
            "late_hold_instability": -0.0,
            "late_hold_speed": -0.0,
            "goal_hold_brake": -0.0,
            "goal_hold_slip": -0.0,
            "goal_hold_support": 0.0
          }
        },
        {
          "step": 3,
          "t_s": 0.06,
          "matched_task": "walk_forward",
          "reward": -2.5188746963912174,
          "done_reason": null,
          "tracked_delta_x": 0.0007522945055642256,
          "tracked_delta_y": -8.90320830713806e-05,
          "tracked_z": 0.24273042387442645,
          "delta_yaw": 0.01220659504916943,
          "imu_pitch": 0.00015104663518426765,
          "imu_roll": -0.0036255105546479046,
          "left_foot_contact": true,
          "right_foot_contact": false,
          "foot_contact_switch_count": 0,
          "left_foot_slip_m_s": 0.032833971083164215,
          "right_foot_slip_m_s": 0.0,
          "max_foot_slip_m_s": 0.032833971083164215,
          "min_robot_geom_floor_clearance_m": -0.00013648524247500925,
          "below_floor_robot_geom_count": 0,
          "worst_below_floor_robot_geom": "",
          "floor_penetration_tolerance_m": 0.005,
          "locomotion_prior_goal_hold_scale": 1.0,
          "locomotion_prior_residual_stability_scale": 1.0,
          "reward_terms": {
            "alive": 1.0,
            "height_track": 0.4857052003939722,
            "velocity_track": 0.026459295352918247,
            "yaw_track": 0.0,
            "contact_cadence": 0.0,
            "stance_contact": 0.0,
            "foot_clearance": 0.0,
            "no_support": -0.0,
            "double_support": -0.0,
            "foot_slip": -0.032833971083164215,
            "foot_spacing": -0.0,
            "self_collision": -0.0,
            "support_contract": -0.0,
            "upright": 0.99999341643634,
            "movement_progress": 0.0010030593407523009,
            "alternating_contact": 0.0,
            "no_progress": -4.996865439560149,
            "gait_prior": 0.0,
            "action_rate": -9.885061299428344e-06,
            "energy": -1.4951244927942753e-05,
            "residual_energy": -0.0009145369403995574,
            "residual_guard_suppression": -0.0,
            "residual_yaw_guard": -0.0,
            "residual_tilt_guard": -0.0,
            "tilt_margin": -0.0,
            "yaw_drift_margin": -0.0013968840252600713,
            "drift": -0.0,
            "late_hold_instability": -0.0,
            "late_hold_speed": -0.0,
            "goal_hold_brake": -0.0,
            "goal_hold_slip": -0.0,
            "goal_hold_support": 0.0
          }
        },
        {
          "step": 4,
          "t_s": 0.08,
          "matched_task": "walk_forward",
          "reward": -2.441084738557344,
          "done_reason": null,
          "tracked_delta_x": 0.0018099597869547367,
          "tracked_delta_y": -0.0005076239969799678,
          "tracked_z": 0.24318487610031642,
          "delta_yaw": 0.02837936256929447,
          "imu_pitch": 0.008410787624565817,
          "imu_roll": -0.010924602917567831,
          "left_foot_contact": true,
          "right_foot_contact": false,
          "foot_contact_switch_count": 0,
          "left_foot_slip_m_s": 0.035936154425144196,
          "right_foot_slip_m_s": 0.0,
          "max_foot_slip_m_s": 0.035936154425144196,
          "min_robot_geom_floor_clearance_m": -0.0004779456021844425,
          "below_floor_robot_geom_count": 0,
          "worst_below_floor_robot_geom": "",
          "floor_penetration_tolerance_m": 0.005,
          "locomotion_prior_goal_hold_scale": 1.0,
          "locomotion_prior_residual_stability_scale": 1.0,
          "reward_terms": {
            "alive": 1.0,
            "height_track": 0.48744071365963404,
            "velocity_track": 0.10577206085638181,
            "yaw_track": 0.0,
            "contact_cadence": 0.0,
            "stance_contact": 0.0,
            "foot_clearance": 0.0,
            "no_support": -0.0,
            "double_support": -0.0,
            "foot_slip": -0.035936154425144196,
            "foot_spacing": -0.0,
            "self_collision": -0.0,
            "support_contract": -0.0,
            "upright": 0.99990495876397,
            "movement_progress": 0.002413279715939649,
            "alternating_contact": 0.0,
            "no_progress": -4.992458500887689,
            "gait_prior": 0.0,
            "action_rate": -8.576023974455893e-06,
            "energy": -1.8926486372947693e-05,
            "residual_energy": -0.0006430791690945625,
            "residual_guard_suppression": -0.0,
            "residual_yaw_guard": -0.0,
            "residual_tilt_guard": -0.0,
            "tilt_margin": -0.0,
            "yaw_drift_margin": -0.00755051456099505,
            "drift": -0.0,
            "late_hold_instability": -0.0,
            "late_hold_speed": -0.0,
            "goal_hold_brake": -0.0,
            "goal_hold_slip": -0.0,
            "goal_hold_support": 0.0
          }
        },
        {
          "step": 5,
          "t_s": 0.1,
          "matched_task": "walk_forward",
          "reward": -2.437020430423459,
          "done_reason": null,
          "tracked_delta_x": 0.0037268217393406087,
          "tracked_delta_y": -0.0010970222157373761,
          "tracked_z": 0.243757298425203,
          "delta_yaw": 0.045141936821765934,
          "imu_pitch": 0.02302913340618476,
          "imu_roll": -0.020108261258405962,
          "left_foot_contact": true,
          "right_foot_contact": false,
          "foot_contact_switch_count": 0,
          "left_foot_slip_m_s": 0.04248657077550888,
          "right_foot_slip_m_s": 0.0,
          "max_foot_slip_m_s": 0.04248657077550888,
          "min_robot_geom_floor_clearance_m": -0.0006366552807656745,
          "below_floor_robot_geom_count": 0,
          "worst_below_floor_robot_geom": "",
          "floor_penetration_tolerance_m": 0.005,
          "locomotion_prior_goal_hold_scale": 1.0,
          "locomotion_prior_residual_stability_scale": 1.0,
          "reward_terms": {
            "alive": 1.0,
            "height_track": 0.48948140601727114,
            "velocity_track": 0.115725467158497,
            "yaw_track": 0.0,
            "contact_cadence": 0.0,
            "stance_contact": 0.0,
            "foot_clearance": 0.0,
            "no_support": -0.0,
            "double_support": -0.0,
            "foot_slip": -0.04248657077550888,
            "foot_spacing": -0.0,
            "self_collision": -0.0,
            "support_contract": -0.0,
            "upright": 0.9995327305586167,
            "movement_progress": 0.004969095652454146,
            "alternating_contact": 0.0,
            "no_progress": -4.984471576086081,
            "gait_prior": 0.0,
            "action_rate": -7.178180385380983e-06,
            "energy": -2.328041195869446e-05,
            "residual_energy": -0.0006362012936733663,
            "residual_guard_suppression": -0.0,
            "residual_yaw_guard": -0.0,
            "residual_tilt_guard": -0.0,
            "tilt_margin": -0.0,
            "yaw_drift_margin": -0.019104323062690377,
            "drift": -0.0,
            "late_hold_instability": -0.0,
            "late_hold_speed": -0.0,
            "goal_hold_brake": -0.0,
            "goal_hold_slip": -0.0,
            "goal_hold_support": 0.0
          }
        },
        {
          "step": 6,
          "t_s": 0.12,
          "matched_task": "walk_forward",
          "reward": -2.532350152686022,
          "done_reason": null,
          "tracked_delta_x": 0.006587358888756103,
          "tracked_delta_y": -0.0018259567682066327,
          "tracked_z": 0.2441801803742747,
          "delta_yaw": 0.06146905581127137,
          "imu_pitch": 0.04051424398574855,
          "imu_roll": -0.03015742658262379,
          "left_foot_contact": true,
          "right_foot_contact": false,
          "foot_contact_switch_count": 0,
          "left_foot_slip_m_s": 0.04370828717947006,
          "right_foot_slip_m_s": 0.0,
          "max_foot_slip_m_s": 0.04370828717947006,
          "min_robot_geom_floor_clearance_m": -0.0006722221233079716,
          "below_floor_robot_geom_count": 0,
          "worst_below_floor_robot_geom": "",
          "floor_penetration_tolerance_m": 0.005,
          "locomotion_prior_goal_hold_scale": 1.0,
          "locomotion_prior_residual_stability_scale": 1.0,
          "reward_terms": {
            "alive": 1.0,
            "height_track": 0.49077161700265637,
            "velocity_track": 0.021638327223615264,
            "yaw_track": 0.0,
            "contact_cadence": 0.0,
            "stance_contact": 0.0,
            "foot_clearance": 0.0,
            "no_support": -0.0,
            "double_support": -0.0,
            "foot_slip": -0.04370828717947006,
            "foot_spacing": -0.0,
            "self_collision": -0.0,
            "support_contract": -0.0,
            "upright": 0.9987250826662875,
            "movement_progress": 0.008783145185008138,
            "alternating_contact": 0.0,
            "no_progress": -4.9725526712968495,
            "gait_prior": 0.0,
            "action_rate": -1.0933690937235952e-05,
            "energy": -2.7610616758465766e-05,
            "residual_energy": -0.0005459017702378333,
            "residual_guard_suppression": -0.0,
            "residual_yaw_guard": -0.0,
            "residual_tilt_guard": -0.0,
            "tilt_margin": -0.0,
            "yaw_drift_margin": -0.0354229202093362,
            "drift": -0.0,
            "late_hold_instability": -0.0,
            "late_hold_speed": -0.0,
            "goal_hold_brake": -0.0,
            "goal_hold_slip": -0.0,
            "goal_hold_support": 0.0
          }
        },
        {
          "step": 7,
          "t_s": 0.14,
          "matched_task": "walk_forward",
          "reward": -2.550897938299649,
          "done_reason": null,
          "tracked_delta_x": 0.01045143290244194,
          "tracked_delta_y": -0.0026714834323924093,
          "tracked_z": 0.24419531521779597,
          "delta_yaw": 0.07654302705934095,
          "imu_pitch": 0.058236460574162006,
          "imu_roll": -0.04026777791286861,
          "left_foot_contact": true,
          "right_foot_contact": false,
          "foot_contact_switch_count": 0,
          "left_foot_slip_m_s": 0.041621528565883636,
          "right_foot_slip_m_s": 0.0,
          "max_foot_slip_m_s": 0.04370828717947006,
          "min_robot_geom_floor_clearance_m": -0.0006455863918996361,
          "below_floor_robot_geom_count": 0,
          "worst_below_floor_robot_geom": "",
          "floor_penetration_tolerance_m": 0.005,
          "locomotion_prior_goal_hold_scale": 1.0,
          "locomotion_prior_residual_stability_scale": 1.0,
          "reward_terms": {
            "alive": 1.0,
            "height_track": 0.49066160770099193,
            "velocity_track": 0.0005331311355010929,
            "yaw_track": 0.0,
            "contact_cadence": 0.0,
            "stance_contact": 0.0,
            "foot_clearance": 0.0,
            "no_support": -0.0,
            "double_support": -0.0,
            "foot_slip": -0.041621528565883636,
            "foot_spacing": -0.0,
            "self_collision": -0.0,
            "support_contract": -0.0,
            "upright": 0.9974954733537631,
            "movement_progress": 0.01393524386992259,
            "alternating_contact": 0.0,
            "no_progress": -4.956452362906492,
            "gait_prior": 0.0,
            "action_rate": -1.4909715391695499e-05,
            "energy": -3.323191404342651e-05,
            "residual_energy": -0.00047478321357630193,
            "residual_guard_suppression": -0.0,
            "residual_yaw_guard": -0.0,
            "residual_tilt_guard": -0.0,
            "tilt_margin": -0.0,
            "yaw_drift_margin": -0.05492657804444062,
            "drift": -0.0,
            "late_hold_instability": -0.0,
            "late_hold_speed": -0.0,
            "goal_hold_brake": -0.0,
            "goal_hold_slip": -0.0,
            "goal_hold_support": 0.0
          }
        },
        {
          "step": 8,
          "t_s": 0.16,
          "matched_task": "walk_forward",
          "reward": -2.5398200626733995,
          "done_reason": null,
          "tracked_delta_x": 0.01534779830677785,
          "tracked_delta_y": -0.003611708869725813,
          "tracked_z": 0.2436757689547451,
          "delta_yaw": 0.08863541954182709,
          "imu_pitch": 0.07432642228952255,
          "imu_roll": -0.049963376194755965,
          "left_foot_contact": true,
          "right_foot_contact": false,
          "foot_contact_switch_count": 0,
          "left_foot_slip_m_s": 0.0348324216902256,
          "right_foot_slip_m_s": 0.0,
          "max_foot_slip_m_s": 0.04370828717947006,
          "min_robot_geom_floor_clearance_m": -0.000534523607438768,
          "below_floor_robot_geom_count": 0,
          "worst_below_floor_robot_geom": "",
          "floor_penetration_tolerance_m": 0.005,
          "locomotion_prior_goal_hold_scale": 1.0,
          "locomotion_prior_residual_stability_scale": 1.0,
          "reward_terms": {
            "alive": 1.0,
            "height_track": 0.4888139601349246,
            "velocity_track": 2.9654258079718976e-06,
            "yaw_track": 0.0,
            "contact_cadence": 0.0,
            "stance_contact": 0.0,
            "foot_clearance": 0.0,
            "no_support": -0.0,
            "double_support": -0.0,
            "foot_slip": -0.0348324216902256,
            "foot_spacing": -0.0,
            "self_collision": -0.0,
            "support_contract": -0.0,
            "upright": 0.9959945984264741,
            "movement_progress": 0.020463731075703803,
            "alternating_contact": 0.0,
            "no_progress": -4.936050840388425,
            "gait_prior": 0.0,
            "action_rate": -1.644431264139712e-05,
            "energy": -4.0528643876314166e-05,
            "residual_energy": -0.0005028552259318531,
            "residual_guard_suppression": -0.0,
            "residual_yaw_guard": -0.0,
            "residual_tilt_guard": -0.0,
            "tilt_margin": -0.0,
            "yaw_drift_margin": -0.07365222747520972,
            "drift": -0.0,
            "late_hold_instability": -0.0,
            "late_hold_speed": -0.0,
            "goal_hold_brake": -0.0,
            "goal_hold_slip": -0.0,
            "goal_hold_support": 0.0
          }
        },
        {
          "step": 9,
          "t_s": 0.18,
          "matched_task": "walk_forward",
          "reward": -2.4963231920060807,
          "done_reason": null,
          "tracked_delta_x": 0.020585051656734174,
          "tracked_delta_y": -0.004850188135769865,
          "tracked_z": 0.2437916924602731,
          "delta_yaw": 0.09132597637123012,
          "imu_pitch": 0.08978958286122109,
          "imu_roll": -0.06120241025185476,
          "left_foot_contact": true,
          "right_foot_contact": false,
          "foot_contact_switch_count": 0,
          "left_foot_slip_m_s": 0.014558051712810993,
          "right_foot_slip_m_s": 0.0,
          "max_foot_slip_m_s": 0.04370828717947006,
          "min_robot_geom_floor_clearance_m": -0.0009250080266664153,
          "below_floor_robot_geom_count": 0,
          "worst_below_floor_robot_geom": "",
          "floor_penetration_tolerance_m": 0.005,
          "locomotion_prior_goal_hold_scale": 1.0,
          "locomotion_prior_residual_stability_scale": 1.0,
          "reward_terms": {
            "alive": 1.0,
            "height_track": 0.48966609673268796,
            "velocity_track": 2.3925724416563203e-05,
            "yaw_track": 0.0,
            "contact_cadence": 0.0,
            "stance_contact": 0.0,
            "foot_clearance": 0.0,
            "no_support": -0.0,
            "double_support": -0.0,
            "foot_slip": -0.014558051712810993,
            "foot_spacing": -0.0,
            "self_collision": -0.0,
            "support_contract": -0.0,
            "upright": 0.994106882234849,
            "movement_progress": 0.027446735542312237,
            "alternating_contact": 0.0,
            "no_progress": -4.914228951430275,
            "gait_prior": 0.0,
            "action_rate": -2.6206605252809824e-06,
            "energy": -4.4519234448671345e-05,
            "residual_energy": -0.0005411208258010447,
            "residual_guard_suppression": -0.0,
            "residual_yaw_guard": -0.0,
            "residual_tilt_guard": -0.0,
            "tilt_margin": -0.0,
            "yaw_drift_margin": -0.07819156837648576,
            "drift": -0.0,
            "late_hold_instability": -0.0,
            "late_hold_speed": -0.0,
            "goal_hold_brake": -0.0,
            "goal_hold_slip": -0.0,
            "goal_hold_support": 0.0
          }
        },
        {
          "step": 10,
          "t_s": 0.2,
          "matched_task": "walk_forward",
          "reward": -2.4890107712478486,
          "done_reason": null,
          "tracked_delta_x": 0.025575347326611392,
          "tracked_delta_y": -0.0065652214697686645,
          "tracked_z": 0.24487934892358018,
          "delta_yaw": 0.09194230979952984,
          "imu_pitch": 0.10218439680732258,
          "imu_roll": -0.07283370483146873,
          "left_foot_contact": true,
          "right_foot_contact": false,
          "foot_contact_switch_count": 0,
          "left_foot_slip_m_s": 0.035231124609708786,
          "right_foot_slip_m_s": 0.0,
          "max_foot_slip_m_s": 0.04370828717947006,
          "min_robot_geom_floor_clearance_m": -0.0009764106556640201,
          "below_floor_robot_geom_count": 0,
          "worst_below_floor_robot_geom": "",
          "floor_penetration_tolerance_m": 0.005,
          "locomotion_prior_goal_hold_scale": 1.0,
          "locomotion_prior_residual_stability_scale": 1.0,
          "reward_terms": {
            "alive": 1.0,
            "height_track": 0.4931065323511179,
            "velocity_track": 8.163750731820976e-05,
            "yaw_track": 0.0,
            "contact_cadence": 0.0,
            "stance_contact": 0.0,
            "foot_clearance": 0.0,
            "no_support": -0.0,
            "double_support": -0.0,
            "foot_slip": -0.035231124609708786,
            "foot_spacing": -0.0,
            "self_collision": -0.0,
            "support_contract": -0.0,
            "upright": 0.992146343230989,
            "movement_progress": 0.03410046310214853,
            "alternating_contact": 0.0,
            "no_progress": -4.893436052805786,
            "gait_prior": 0.0,
            "action_rate": -1.3917595788370819e-06,
            "energy": -4.567287862300873e-05,
            "residual_energy": -0.00048098978004418314,
            "residual_guard_suppression": -0.0,
            "residual_yaw_guard": -0.0,
            "residual_tilt_guard": -0.0,
            "tilt_margin": -0.0,
            "yaw_drift_margin": -0.07925051560568176,
            "drift": -0.0,
            "late_hold_instability": -0.0,
            "late_hold_speed": -0.0,
            "goal_hold_brake": -0.0,
            "goal_hold_slip": -0.0,
            "goal_hold_support": 0.0
          }
        },
        {
          "step": 11,
          "t_s": 0.22,
          "matched_task": "walk_forward",
          "reward": -2.4643049165127335,
          "done_reason": null,
          "tracked_delta_x": 0.030464867752218055,
          "tracked_delta_y": -0.008681906989567428,
          "tracked_z": 0.2461593787026876,
          "delta_yaw": 0.09266172932983195,
          "imu_pitch": 0.11066753684106317,
          "imu_roll": -0.08273493162350563,
          "left_foot_contact": true,
          "right_foot_contact": false,
          "foot_contact_switch_count": 0,
          "left_foot_slip_m_s": 0.03780209645628929,
          "right_foot_slip_m_s": 0.0,
          "max_foot_slip_m_s": 0.04370828717947006,
          "min_robot_geom_floor_clearance_m": -0.0008274402816363172,
          "below_floor_robot_geom_count": 0,
          "worst_below_floor_robot_geom": "",
          "floor_penetration_tolerance_m": 0.005,
          "locomotion_prior_goal_hold_scale": 1.0,
          "locomotion_prior_residual_stability_scale": 1.0,
          "reward_terms": {
            "alive": 1.0,
            "height_track": 0.496164962181781,
            "velocity_track": 0.00012674932937417532,
            "yaw_track": 0.0,
            "contact_cadence": 0.0,
            "stance_contact": 0.0,
            "foot_clearance": 0.0,
            "no_support": -0.0,
            "double_support": -0.0,
            "foot_slip": -0.03780209645628929,
            "foot_spacing": -0.0,
            "self_collision": -0.0,
            "support_contract": -0.0,
            "upright": 0.9904829379230878,
            "movement_progress": 0.04061982366962408,
            "alternating_contact": 0.0,
            "no_progress": -4.873063051032425,
            "gait_prior": 0.0,
            "action_rate": -3.212520095985383e-06,
            "energy": -4.578275606036186e-05,
            "residual_energy": -0.00028965857927687466,
            "residual_guard_suppression": -0.0,
            "residual_yaw_guard": -0.0,
            "residual_tilt_guard": -0.0,
            "tilt_margin": -0.0,
            "yaw_drift_margin": -0.08049558827245348,
            "drift": -0.0,
            "late_hold_instability": -0.0,
            "late_hold_speed": -0.0,
            "goal_hold_brake": -0.0,
            "goal_hold_slip": -0.0,
            "goal_hold_support": 0.0
          }
        },
        {
          "step": 12,
          "t_s": 0.24,
          "matched_task": "walk_forward",
          "reward": -2.4416654542629255,
          "done_reason": null,
          "tracked_delta_x": 0.03536678579882433,
          "tracked_delta_y": -0.011097347564220855,
          "tracked_z": 0.24731255463176982,
          "delta_yaw": 0.09478399869778208,
          "imu_pitch": 0.11454775777112225,
          "imu_roll": -0.08778912150509083,
          "left_foot_contact": true,
          "right_foot_contact": false,
          "foot_contact_switch_count": 0,
          "left_foot_slip_m_s": 0.03966972604393959,
          "right_foot_slip_m_s": 0.0,
          "max_foot_slip_m_s": 0.04370828717947006,
          "min_robot_geom_floor_clearance_m": -0.000721961705910568,
          "below_floor_robot_geom_count": 0,
          "worst_below_floor_robot_geom": "",
          "floor_penetration_tolerance_m": 0.005,
          "locomotion_prior_goal_hold_scale": 1.0,
          "locomotion_prior_residual_stability_scale": 1.0,
          "reward_terms": {
            "alive": 1.0,
            "height_track": 0.4981418790678092,
            "velocity_track": 0.00011316229160591797,
            "yaw_track": 0.0,
            "contact_cadence": 0.0,
            "stance_contact": 0.0,
            "foot_clearance": 0.0,
            "no_support": -0.0,
            "double_support": -0.0,
            "foot_slip": -0.03966972604393959,
            "foot_spacing": -0.0,
            "self_collision": -0.0,
            "support_contract": -0.0,
            "upright": 0.9896208225015813,
            "movement_progress": 0.04715571439843244,
            "alternating_contact": 0.0,
            "no_progress": -4.852638392504899,
            "gait_prior": 0.0,
            "action_rate": -6.436558323912322e-06,
            "energy": -4.54154871404171e-05,
            "residual_energy": -0.00011200184235349298,
            "residual_guard_suppression": -0.0,
            "residual_yaw_guard": -0.0,
            "residual_tilt_guard": -0.0,
            "tilt_margin": -0.0,
            "yaw_drift_margin": -0.08422506008569831,
            "drift": -0.0,
            "late_hold_instability": -0.0,
            "late_hold_speed": -0.0,
            "goal_hold_brake": -0.0,
            "goal_hold_slip": -0.0,
            "goal_hold_support": 0.0
          }
        },
        {
          "step": 13,
          "t_s": 0.26,
          "matched_task": "walk_forward",
          "reward": -2.426509418158211,
          "done_reason": null,
          "tracked_delta_x": 0.04038203160306781,
          "tracked_delta_y": -0.013777976895845747,
          "tracked_z": 0.2482619591238107,
          "delta_yaw": 0.098681285520722,
          "imu_pitch": 0.11299732478837371,
          "imu_roll": -0.08636143067321322,
          "left_foot_contact": true,
          "right_foot_contact": false,
          "foot_contact_switch_count": 0,
          "left_foot_slip_m_s": 0.046113915741443634,
          "right_foot_slip_m_s": 0.0,
          "max_foot_slip_m_s": 0.046113915741443634,
          "min_robot_geom_floor_clearance_m": -0.000680830843082519,
          "below_floor_robot_geom_count": 0,
          "worst_below_floor_robot_geom": "",
          "floor_penetration_tolerance_m": 0.005,
          "locomotion_prior_goal_hold_scale": 1.0,
          "locomotion_prior_residual_stability_scale": 1.0,
          "reward_terms": {
            "alive": 1.0,
            "height_track": 0.4992349358966534,
            "velocity_track": 6.0140254508564624e-05,
            "yaw_track": 0.0,
            "contact_cadence": 0.0,
            "stance_contact": 0.0,
            "foot_clearance": 0.0,
            "no_support": -0.0,
            "double_support": -0.0,
            "foot_slip": -0.046113915741443634,
            "foot_spacing": -0.0,
            "self_collision": -0.0,
            "support_contract": -0.0,
            "upright": 0.9899195287507682,
            "movement_progress": 0.053842708804090415,
            "alternating_contact": 0.0,
            "no_progress": -4.831741534987217,
            "gait_prior": 0.0,
            "action_rate": -1.0634197387844324e-05,
            "energy": -4.520778730511665e-05,
            "residual_energy": -0.0003617256006691605,
            "residual_guard_suppression": -0.0,
            "residual_yaw_guard": -0.0,
            "residual_tilt_guard": -0.0,
            "tilt_margin": -0.0,
            "yaw_drift_margin": -0.09129371355020865,
            "drift": -0.0,
            "late_hold_instability": -0.0,
            "late_hold_speed": -0.0,
            "goal_hold_brake": -0.0,
            "goal_hold_slip": -0.0,
            "goal_hold_support": 0.0
          }
        },
        {
          "step": 14,
          "t_s": 0.28,
          "matched_task": "walk_forward",
          "reward": -2.4178662510321516,
          "done_reason": null,
          "tracked_delta_x": 0.04559070659076367,
          "tracked_delta_y": -0.01671423131096846,
          "tracked_z": 0.24896846482541538,
          "delta_yaw": 0.10443360590636674,
          "imu_pitch": 0.10583793767477276,
          "imu_roll": -0.07721408153703542,
          "left_foot_contact": true,
          "right_foot_contact": false,
          "foot_contact_switch_count": 0,
          "left_foot_slip_m_s": 0.05609232559800148,
          "right_foot_slip_m_s": 0.0,
          "max_foot_slip_m_s": 0.05609232559800148,
          "min_robot_geom_floor_clearance_m": -0.0006683166710884057,
          "below_floor_robot_geom_count": 0,
          "worst_below_floor_robot_geom": "",
          "floor_penetration_tolerance_m": 0.005,
          "locomotion_prior_goal_hold_scale": 1.0,
          "locomotion_prior_residual_stability_scale": 1.0,
          "reward_terms": {
            "alive": 1.0,
            "height_track": 0.49973334578057743,
            "velocity_track": 2.125003314523946e-05,
            "yaw_track": 0.0,
            "contact_cadence": 0.0,
            "stance_contact": 0.0,
            "foot_clearance": 0.0,
            "no_support": -0.0,
            "double_support": -0.0,
            "foot_slip": -0.05609232559800148,
            "foot_spacing": -0.0,
            "self_collision": -0.0,
            "support_contract": -0.0,
            "upright": 0.9914415375890022,
            "movement_progress": 0.0607876087876849,
            "alternating_contact": 0.0,
            "no_progress": -4.810038722538485,
            "gait_prior": 0.0,
            "action_rate": -1.448002178221941e-05,
            "energy": -4.6161334961652756e-05,
            "residual_energy": -0.0014110095798969269,
            "residual_guard_suppression": -0.0,
            "residual_yaw_guard": -0.0,
            "residual_tilt_guard": -0.0,
            "tilt_margin": -0.0,
            "yaw_drift_margin": -0.10224729414943425,
            "drift": -0.0,
            "late_hold_instability": -0.0,
            "late_hold_speed": -0.0,
            "goal_hold_brake": -0.0,
            "goal_hold_slip": -0.0,
            "goal_hold_support": 0.0
          }
        },
        {
          "step": 15,
          "t_s": 0.3,
          "matched_task": "walk_forward",
          "reward": -2.4151195504191394,
          "done_reason": null,
          "tracked_delta_x": 0.05101957804590109,
          "tracked_delta_y": -0.019917488157902563,
          "tracked_z": 0.24934841321206486,
          "delta_yaw": 0.11208460052616841,
          "imu_pitch": 0.09451978903520039,
          "imu_roll": -0.05966881588634491,
          "left_foot_contact": true,
          "right_foot_contact": false,
          "foot_contact_switch_count": 0,
          "left_foot_slip_m_s": 0.06853589415550232,
          "right_foot_slip_m_s": 0.0,
          "max_foot_slip_m_s": 0.06853589415550232,
          "min_robot_geom_floor_clearance_m": -0.0006620764060459722,
          "below_floor_robot_geom_count": 0,
          "worst_below_floor_robot_geom": "",
          "floor_penetration_tolerance_m": 0.005,
          "locomotion_prior_goal_hold_scale": 1.0,
          "locomotion_prior_residual_stability_scale": 1.0,
          "reward_terms": {
            "alive": 1.0,
            "height_track": 0.49988762251167806,
            "velocity_track": 6.772474409754437e-06,
            "yaw_track": 0.0,
            "contact_cadence": 0.0,
            "stance_contact": 0.0,
            "foot_clearance": 0.0,
            "no_support": -0.0,
            "double_support": -0.0,
            "foot_slip": -0.06853589415550232,
            "foot_spacing": -0.0,
            "self_collision": -0.0,
            "support_contract": -0.0,
            "upright": 0.9937646175396908,
            "movement_progress": 0.06802610406120145,
            "alternating_contact": 0.0,
            "no_progress": -4.787418424808745,
            "gait_prior": 0.0,
            "action_rate": -1.6768588684499266e-05,
            "energy": -4.897363856434822e-05,
            "residual_energy": -0.0030068776104599237,
            "residual_guard_suppression": -0.0,
            "residual_yaw_guard": -0.0,
            "residual_tilt_guard": -0.0,
            "tilt_margin": -0.0,
            "yaw_drift_margin": -0.11777772820416327,
            "drift": -0.0,
            "late_hold_instability": -0.0,
            "late_hold_speed": -0.0,
            "goal_hold_brake": -0.0,
            "goal_hold_slip": -0.0,
            "goal_hold_support": 0.0
          }
        },
        {
          "step": 16,
          "t_s": 0.32,
          "matched_task": "walk_forward",
          "reward": -2.4157182561558055,
          "done_reason": null,
          "tracked_delta_x": 0.056667271251106585,
          "tracked_delta_y": -0.023399956851313165,
          "tracked_z": 0.24927286767653042,
          "delta_yaw": 0.12138987850591479,
          "imu_pitch": 0.08119264324378404,
          "imu_roll": -0.03300333142492974,
          "left_foot_contact": true,
          "right_foot_contact": false,
          "foot_contact_switch_count": 0,
          "left_foot_slip_m_s": 0.08096117526292801,
          "right_foot_slip_m_s": 0.0,
          "max_foot_slip_m_s": 0.08096117526292801,
          "min_robot_geom_floor_clearance_m": -0.0006508528308024515,
          "below_floor_robot_geom_count": 0,
          "worst_below_floor_robot_geom": "",
          "floor_penetration_tolerance_m": 0.005,
          "locomotion_prior_goal_hold_scale": 1.0,
          "locomotion_prior_residual_stability_scale": 1.0,
          "reward_terms": {
            "alive": 1.0,
            "height_track": 0.49983901893272153,
            "velocity_track": 2.823182231684941e-06,
            "yaw_track": 0.0,
            "contact_cadence": 0.0,
            "stance_contact": 0.0,
            "foot_clearance": 0.0,
            "no_support": -0.0,
            "double_support": -0.0,
            "foot_slip": -0.08096117526292801,
            "foot_spacing": -0.0,
            "self_collision": -0.0,
            "support_contract": -0.0,
            "upright": 0.9961629211224913,
            "movement_progress": 0.07555636166814211,
            "alternating_contact": 0.0,
            "no_progress": -4.7638863697870555,
            "gait_prior": 0.0,
            "action_rate": -1.6931906575337052e-05,
            "energy": -5.37153035402298e-05,
            "residual_energy": -0.00421585189178586,
            "residual_guard_suppression": -0.0,
            "residual_yaw_guard": -0.0,
            "residual_tilt_guard": -0.0,
            "tilt_margin": -0.0,
            "yaw_drift_margin": -0.13814533690950706,
            "drift": -0.0,
            "late_hold_instability": -0.0,
            "late_hold_speed": -0.0,
            "goal_hold_brake": -0.0,
            "goal_hold_slip": -0.0,
            "goal_hold_support": 0.0
          }
        },
        {
          "step": 17,
          "t_s": 0.34,
          "matched_task": "walk_forward",
          "reward": -1.534128336810792,
          "done_reason": null,
          "tracked_delta_x": 0.062322297809073036,
          "tracked_delta_y": -0.026932554755354776,
          "tracked_z": 0.2500882459662966,
          "delta_yaw": 0.11707283648853349,
          "imu_pitch": 0.06814078420806964,
          "imu_roll": -0.012130242274288744,
          "left_foot_contact": false,
          "right_foot_contact": true,
          "foot_contact_switch_count": 1,
          "left_foot_slip_m_s": 0.0,
          "right_foot_slip_m_s": 0.20772160589694977,
          "max_foot_slip_m_s": 0.20772160589694977,
          "min_robot_geom_floor_clearance_m": -0.0016291755274510274,
          "below_floor_robot_geom_count": 0,
          "worst_below_floor_robot_geom": "",
          "floor_penetration_tolerance_m": 0.005,
          "locomotion_prior_goal_hold_scale": 1.0,
          "locomotion_prior_residual_stability_scale": 1.0,
          "reward_terms": {
            "alive": 1.0,
            "height_track": 0.4999782242530013,
            "velocity_track": 2.7107873681855784e-05,
            "yaw_track": 0.0,
            "contact_cadence": 0.0,
            "stance_contact": 0.0,
            "foot_clearance": 0.0,
            "no_support": -0.0,
            "double_support": -0.0,
            "foot_slip": -0.20772160589694977,
            "foot_spacing": -0.0,
            "self_collision": -0.0,
            "support_contract": -0.0,
            "upright": 0.9976059151634245,
            "movement_progress": 0.27006329050598316,
            "alternating_contact": 0.0,
            "no_progress": -3.961295036515449,
            "gait_prior": 0.0,
            "action_rate": -1.5840382548049093e-05,
            "energy": -5.987006425857544e-05,
            "residual_energy": -0.00421631196513772,
            "residual_guard_suppression": -0.0,
            "residual_yaw_guard": -0.0,
            "residual_tilt_guard": -0.0,
            "tilt_margin": -0.0,
            "yaw_drift_margin": -0.12849420978253964,
            "drift": -0.0,
            "late_hold_instability": -0.0,
            "late_hold_speed": -0.0,
            "goal_hold_brake": -0.0,
            "goal_hold_slip": -0.0,
            "goal_hold_support": 0.0
          }
        },
        {
          "step": 18,
          "t_s": 0.36,
          "matched_task": "walk_forward",
          "reward": -1.2700176526817664,
          "done_reason": null,
          "tracked_delta_x": 0.06776767487885829,
          "tracked_delta_y": -0.03015370550910461,
          "tracked_z": 0.2520249231060536,
          "delta_yaw": 0.09639801472511023,
          "imu_pitch": 0.052882347942291345,
          "imu_roll": -0.012865684869063681,
          "left_foot_contact": false,
          "right_foot_contact": true,
          "foot_contact_switch_count": 1,
          "left_foot_slip_m_s": 0.0,
          "right_foot_slip_m_s": 0.10091662406921387,
          "max_foot_slip_m_s": 0.20772160589694977,
          "min_robot_geom_floor_clearance_m": -0.001424361319799325,
          "below_floor_robot_geom_count": 0,
          "worst_below_floor_robot_geom": "",
          "floor_penetration_tolerance_m": 0.005,
          "locomotion_prior_goal_hold_scale": 1.0,
          "locomotion_prior_residual_stability_scale": 1.0,
          "reward_terms": {
            "alive": 1.0,
            "height_track": 0.4986535214304748,
            "velocity_track": 4.2623512130817776e-05,
            "yaw_track": 0.0,
            "contact_cadence": 0.0,
            "stance_contact": 0.0,
            "foot_clearance": 0.0,
            "no_support": -0.0,
            "double_support": -0.0,
            "foot_slip": -0.10091662406921387,
            "foot_spacing": -0.0,
            "self_collision": -0.0,
            "support_contract": -0.0,
            "upright": 0.9985194083826465,
            "movement_progress": 0.2936599244750526,
            "alternating_contact": 0.0,
            "no_progress": -3.870538752019028,
            "gait_prior": 0.0,
            "action_rate": -7.3891080683097245e-06,
            "energy": -6.562232226133347e-05,
            "residual_energy": -0.0022468313109129667,
            "residual_guard_suppression": -0.0,
            "residual_yaw_guard": -0.0,
            "residual_tilt_guard": -0.0,
            "tilt_margin": -0.0,
            "yaw_drift_margin": -0.08711791165258657,
            "drift": -0.0,
            "late_hold_instability": -0.0,
            "late_hold_speed": -0.0,
            "goal_hold_brake": -0.0,
            "goal_hold_slip": -0.0,
            "goal_hold_support": 0.0
          }
        },
        {
          "step": 19,
          "t_s": 0.38,
          "matched_task": "walk_forward",
          "reward": -1.1113334410181501,
          "done_reason": null,
          "tracked_delta_x": 0.07303115081613525,
          "tracked_delta_y": -0.03291415486782364,
          "tracked_z": 0.2535803762437842,
          "delta_yaw": 0.07155562849818431,
          "imu_pitch": 0.03590432236340975,
          "imu_roll": -0.023335093710948926,
          "left_foot_contact": false,
          "right_foot_contact": true,
          "foot_contact_switch_count": 1,
          "left_foot_slip_m_s": 0.0,
          "right_foot_slip_m_s": 0.09063930809497833,
          "max_foot_slip_m_s": 0.20772160589694977,
          "min_robot_geom_floor_clearance_m": -0.0010298497918763173,
          "below_floor_robot_geom_count": 0,
          "worst_below_floor_robot_geom": "",
          "floor_penetration_tolerance_m": 0.005,
          "locomotion_prior_goal_hold_scale": 1.0,
          "locomotion_prior_residual_stability_scale": 1.0,
          "reward_terms": {
            "alive": 1.0,
            "height_track": 0.49620594463098305,
            "velocity_track": 6.393062955539694e-05,
            "yaw_track": 0.0,
            "contact_cadence": 0.0,
            "stance_contact": 0.0,
            "foot_clearance": 0.0,
            "no_support": -0.0,
            "double_support": -0.0,
            "foot_slip": -0.09063930809497833,
            "foot_spacing": -0.0,
            "self_collision": -0.0,
            "support_contract": -0.0,
            "upright": 0.9990834335761533,
            "movement_progress": 0.3164683202032527,
            "alternating_contact": 0.0,
            "no_progress": -3.782814153064413,
            "gait_prior": 0.0,
            "action_rate": -5.851215100847185e-06,
            "energy": -6.108261272311211e-05,
            "residual_energy": -0.001632725354284048,
            "residual_guard_suppression": -0.0,
            "residual_yaw_guard": -0.0,
            "residual_tilt_guard": -0.0,
            "tilt_margin": -0.0,
            "yaw_drift_margin": -0.04800194971659531,
            "drift": -0.0,
            "late_hold_instability": -0.0,
            "late_hold_speed": -0.0,
            "goal_hold_brake": -0.0,
            "goal_hold_slip": -0.0,
            "goal_hold_support": 0.0
          }
        },
        {
          "step": 20,
          "t_s": 0.4,
          "matched_task": "walk_forward",
          "reward": -0.969107251964411,
          "done_reason": null,
          "tracked_delta_x": 0.07810458109234325,
          "tracked_delta_y": -0.03515838109009499,
          "tracked_z": 0.25443780160504786,
          "delta_yaw": 0.04432940872146811,
          "imu_pitch": 0.020209020862450824,
          "imu_roll": -0.038097363728787005,
          "left_foot_contact": false,
          "right_foot_contact": true,
          "foot_contact_switch_count": 1,
          "left_foot_slip_m_s": 0.0,
          "right_foot_slip_m_s": 0.08361794054508209,
          "max_foot_slip_m_s": 0.20772160589694977,
          "min_robot_geom_floor_clearance_m": -0.0008201085203675199,
          "below_floor_robot_geom_count": 0,
          "worst_below_floor_robot_geom": "",
          "floor_penetration_tolerance_m": 0.005,
          "locomotion_prior_goal_hold_scale": 1.0,
          "locomotion_prior_residual_stability_scale": 1.0,
          "reward_terms": {
            "alive": 1.0,
            "height_track": 0.49442773596671397,
            "velocity_track": 0.00012754346103565159,
            "yaw_track": 0.0,
            "contact_cadence": 0.0,
            "stance_contact": 0.0,
            "foot_clearance": 0.0,
            "no_support": -0.0,
            "double_support": -0.0,
            "foot_slip": -0.08361794054508209,
            "foot_spacing": -0.0,
            "self_collision": -0.0,
            "support_contract": -0.0,
            "upright": 0.9990703360638342,
            "movement_progress": 0.33845318473348746,
            "alternating_contact": 0.0,
            "no_progress": -3.698256981794279,
            "gait_prior": 0.0,
            "action_rate": -1.4846497215330601e-05,
            "energy": -4.886121675372124e-05,
            "residual_energy": -0.0008246426586993039,
            "residual_guard_suppression": -0.0,
            "residual_yaw_guard": -0.0,
            "residual_tilt_guard": -0.0,
            "tilt_margin": -0.0,
            "yaw_drift_margin": -0.01842277947745287,
            "drift": -0.0,
            "late_hold_instability": -0.0,
            "late_hold_speed": -0.0,
            "goal_hold_brake": -0.0,
            "goal_hold_slip": -0.0,
            "goal_hold_support": 0.0
          }
        },
        {
          "step": 21,
          "t_s": 0.42,
          "matched_task": "walk_forward",
          "reward": -0.8425992512734292,
          "done_reason": null,
          "tracked_delta_x": 0.08285947308857934,
          "tracked_delta_y": -0.0368119227166032,
          "tracked_z": 0.2546911946876601,
          "delta_yaw": 0.015697722269032426,
          "imu_pitch": 0.011709622779760056,
          "imu_roll": -0.053433734207506745,
          "left_foot_contact": false,
          "right_foot_contact": true,
          "foot_contact_switch_count": 1,
          "left_foot_slip_m_s": 0.0,
          "right_foot_slip_m_s": 0.07294156402349472,
          "max_foot_slip_m_s": 0.20772160589694977,
          "min_robot_geom_floor_clearance_m": -0.0007753033857185489,
          "below_floor_robot_geom_count": 0,
          "worst_below_floor_robot_geom": "",
          "floor_penetration_tolerance_m": 0.005,
          "locomotion_prior_goal_hold_scale": 1.0,
          "locomotion_prior_residual_stability_scale": 1.0,
          "reward_terms": {
            "alive": 1.0,
            "height_track": 0.4939151332138896,
            "velocity_track": 0.0005979878550731462,
            "yaw_track": 0.0,
            "contact_cadence": 0.0,
            "stance_contact": 0.0,
            "foot_clearance": 0.0,
            "no_support": -0.0,
            "double_support": -0.0,
            "foot_slip": -0.07294156402349472,
            "foot_spacing": -0.0,
            "self_collision": -0.0,
            "support_contract": -0.0,
            "upright": 0.9985042986548163,
            "movement_progress": 0.3590577167171771,
            "alternating_contact": 0.0,
            "no_progress": -3.619008781857011,
            "gait_prior": 0.0,
            "action_rate": -1.575584872625768e-05,
            "energy": -3.814153000712395e-05,
            "residual_energy": -0.00035997116356156766,
            "residual_guard_suppression": -0.0,
            "residual_yaw_guard": -0.0,
            "residual_tilt_guard": -0.0,
            "tilt_margin": -0.0,
            "yaw_drift_margin": -0.002310173291584467,
            "drift": -0.0,
            "late_hold_instability": -0.0,
            "late_hold_speed": -0.0,
            "goal_hold_brake": -0.0,
            "goal_hold_slip": -0.0,
            "goal_hold_support": 0.0
          }
        },
        {
          "step": 22,
          "t_s": 0.44,
          "matched_task": "walk_forward",
          "reward": -0.7368281420679539,
          "done_reason": null,
          "tracked_delta_x": 0.08734379021942841,
          "tracked_delta_y": -0.03780961957378422,
          "tracked_z": 0.2545744455722081,
          "delta_yaw": -0.01352795237715959,
          "imu_pitch": 0.009898895668474524,
          "imu_roll": -0.06797991537852631,
          "left_foot_contact": false,
          "right_foot_contact": true,
          "foot_contact_switch_count": 1,
          "left_foot_slip_m_s": 0.0,
          "right_foot_slip_m_s": 0.06253722310066223,
          "max_foot_slip_m_s": 0.20772160589694977,
          "min_robot_geom_floor_clearance_m": -0.000790977819480683,
          "below_floor_robot_geom_count": 0,
          "worst_below_floor_robot_geom": "",
          "floor_penetration_tolerance_m": 0.005,
          "locomotion_prior_goal_hold_scale": 1.0,
          "locomotion_prior_residual_stability_scale": 1.0,
          "reward_terms": {
            "alive": 1.0,
            "height_track": 0.49428001735931265,
            "velocity_track": 0.001600753831139641,
            "yaw_track": 0.0,
            "contact_cadence": 0.0,
            "stance_contact": 0.0,
            "foot_clearance": 0.0,
            "no_support": -0.0,
            "double_support": -0.0,
            "foot_slip": -0.06253722310066223,
            "foot_spacing": -0.0,
            "self_collision": -0.0,
            "support_contract": -0.0,
            "upright": 0.9976413747493016,
            "movement_progress": 0.3784897576175232,
            "alternating_contact": 0.0,
            "no_progress": -3.5442701630095264,
            "gait_prior": 0.0,
            "action_rate": -8.84155509993434e-06,
            "energy": -3.209274262189865e-05,
            "residual_energy": -0.00027604869683273137,
            "residual_guard_suppression": -0.0,
            "residual_yaw_guard": -0.0,
            "residual_tilt_guard": -0.0,
            "tilt_margin": -0.0,
            "yaw_drift_margin": -0.0017156765204877915,
            "drift": -0.0,
            "late_hold_instability": -0.0,
            "late_hold_speed": -0.0,
            "goal_hold_brake": -0.0,
            "goal_hold_slip": -0.0,
            "goal_hold_support": 0.0
          }
        },
        {
          "step": 23,
          "t_s": 0.46,
          "matched_task": "walk_forward",
          "reward": -0.651109215335753,
          "done_reason": null,
          "tracked_delta_x": 0.09169106165706928,
          "tracked_delta_y": -0.03811999940676453,
          "tracked_z": 0.25425828126006406,
          "delta_yaw": -0.04236190109418396,
          "imu_pitch": 0.012656601281252218,
          "imu_roll": -0.08121998415324828,
          "left_foot_contact": false,
          "right_foot_contact": true,
          "foot_contact_switch_count": 1,
          "left_foot_slip_m_s": 0.0,
          "right_foot_slip_m_s": 0.05371050164103508,
          "max_foot_slip_m_s": 0.20772160589694977,
          "min_robot_geom_floor_clearance_m": -0.000807637562413515,
          "below_floor_robot_geom_count": 0,
          "worst_below_floor_robot_geom": "",
          "floor_penetration_tolerance_m": 0.005,
          "locomotion_prior_goal_hold_scale": 1.0,
          "locomotion_prior_residual_stability_scale": 1.0,
          "reward_terms": {
            "alive": 1.0,
            "height_track": 0.4950798244478529,
            "velocity_track": 0.0026223457911108204,
            "yaw_track": 0.0,
            "contact_cadence": 0.0,
            "stance_contact": 0.0,
            "foot_clearance": 0.0,
            "no_support": -0.0,
            "double_support": -0.0,
            "foot_slip": -0.05371050164103508,
            "foot_spacing": -0.0,
            "self_collision": -0.0,
            "support_contract": -0.0,
            "upright": 0.9966236401886013,
            "movement_progress": 0.39732793384730025,
            "alternating_contact": 0.0,
            "no_progress": -3.4718156390488453,
            "gait_prior": 0.0,
            "action_rate": -6.08606671448797e-06,
            "energy": -2.891160361468792e-05,
            "residual_energy": -0.00037809627247042954,
            "residual_guard_suppression": -0.0,
            "residual_yaw_guard": -0.0,
            "residual_tilt_guard": -0.0,
            "tilt_margin": -0.0,
            "yaw_drift_margin": -0.01682372497793835,
            "drift": -0.0,
            "late_hold_instability": -0.0,
            "late_hold_speed": -0.0,
            "goal_hold_brake": -0.0,
            "goal_hold_slip": -0.0,
            "goal_hold_support": 0.0
          }
        },
        {
          "step": 24,
          "t_s": 0.48,
          "matched_task": "walk_forward",
          "reward": -0.5821434377621386,
          "done_reason": null,
          "tracked_delta_x": 0.09602192481437286,
          "tracked_delta_y": -0.03772906605500027,
          "tracked_z": 0.25382330578263523,
          "delta_yaw": -0.0701654866496221,
          "imu_pitch": 0.018464513255885592,
          "imu_roll": -0.09291337304624729,
          "left_foot_contact": false,
          "right_foot_contact": true,
          "foot_contact_switch_count": 1,
          "left_foot_slip_m_s": 0.0,
          "right_foot_slip_m_s": 0.04656204208731651,
          "max_foot_slip_m_s": 0.20772160589694977,
          "min_robot_geom_floor_clearance_m": -0.000812428874382147,
          "below_floor_robot_geom_count": 0,
          "worst_below_floor_robot_geom": "",
          "floor_penetration_tolerance_m": 0.005,
          "locomotion_prior_goal_hold_scale": 1.0,
          "locomotion_prior_residual_stability_scale": 1.0,
          "reward_terms": {
            "alive": 1.0,
            "height_track": 0.49606024584418484,
            "velocity_track": 0.0030634873559057412,
            "yaw_track": 0.0,
            "contact_cadence": 0.0,
            "stance_contact": 0.0,
            "foot_clearance": 0.0,
            "no_support": -0.0,
            "double_support": -0.0,
            "foot_slip": -0.04656204208731651,
            "foot_spacing": -0.0,
            "self_collision": -0.0,
            "support_contract": -0.0,
            "upright": 0.9955169279368286,
            "movement_progress": 0.41609500752894907,
            "alternating_contact": 0.0,
            "no_progress": -3.399634586427119,
            "gait_prior": 0.0,
            "action_rate": -6.076731369830668e-06,
            "energy": -2.7627578005194666e-05,
            "residual_energy": -0.0004938156343996525,
            "residual_guard_suppression": -0.0,
            "residual_yaw_guard": -0.0,
            "residual_tilt_guard": -0.0,
            "tilt_margin": -0.0,
            "yaw_drift_margin": -0.04615495796979653,
            "drift": -0.0,
            "late_hold_instability": -0.0,
            "late_hold_speed": -0.0,
            "goal_hold_brake": -0.0,
            "goal_hold_slip": -0.0,
            "goal_hold_support": 0.0
          }
        },
        {
          "step": 25,
          "t_s": 0.5,
          "matched_task": "walk_forward",
          "reward": -0.5263755619125986,
          "done_reason": null,
          "tracked_delta_x": 0.10043264637772266,
          "tracked_delta_y": -0.036624028253708564,
          "tracked_z": 0.25329610006394976,
          "delta_yaw": -0.09673513084542155,
          "imu_pitch": 0.026587861768454173,
          "imu_roll": -0.10301978470312079,
          "left_foot_contact": false,
          "right_foot_contact": true,
          "foot_contact_switch_count": 1,
          "left_foot_slip_m_s": 0.0,
          "right_foot_slip_m_s": 0.04154001921415329,
          "max_foot_slip_m_s": 0.20772160589694977,
          "min_robot_geom_floor_clearance_m": -0.0008079684633779394,
          "below_floor_robot_geom_count": 0,
          "worst_below_floor_robot_geom": "",
          "floor_penetration_tolerance_m": 0.005,
          "locomotion_prior_goal_hold_scale": 1.0,
          "locomotion_prior_residual_stability_scale": 1.0,
          "reward_terms": {
            "alive": 1.0,
            "height_track": 0.4970986173675574,
            "velocity_track": 0.00287630054492978,
            "yaw_track": 0.0,
            "contact_cadence": 0.0,
            "stance_contact": 0.0,
            "foot_clearance": 0.0,
            "no_support": -0.0,
            "double_support": -0.0,
            "foot_slip": -0.04154001921415329,
            "foot_spacing": -0.0,
            "self_collision": -0.0,
            "support_contract": -0.0,
            "upright": 0.9943465910343426,
            "movement_progress": 0.43520813430346483,
            "alternating_contact": 0.0,
            "no_progress": -3.326122560371289,
            "gait_prior": 0.0,
            "action_rate": -7.045336533337832e-06,
            "energy": -2.795754373073578e-05,
            "residual_energy": -0.00047932076267898083,
            "residual_guard_suppression": -0.0,
            "residual_yaw_guard": -0.0,
            "residual_tilt_guard": -0.0,
            "tilt_margin": -0.0,
            "yaw_drift_margin": -0.08772830193450776,
            "drift": -0.0,
            "late_hold_instability": -0.0,
            "late_hold_speed": -0.0,
            "goal_hold_brake": -0.0,
            "goal_hold_slip": -0.0,
            "goal_hold_support": 0.0
          }
        },
        {
          "step": 26,
          "t_s": 0.52,
          "matched_task": "walk_forward",
          "reward": -0.4817445156356107,
          "done_reason": null,
          "tracked_delta_x": 0.10500612155185426,
          "tracked_delta_y": -0.0347980655133979,
          "tracked_z": 0.25266964441903206,
          "delta_yaw": -0.12213959341371236,
          "imu_pitch": 0.036557706955706606,
          "imu_roll": -0.11198277347210689,
          "left_foot_contact": false,
          "right_foot_contact": true,
          "foot_contact_switch_count": 1,
          "left_foot_slip_m_s": 0.0,
          "right_foot_slip_m_s": 0.04009133204817772,
          "max_foot_slip_m_s": 0.20772160589694977,
          "min_robot_geom_floor_clearance_m": -0.0007968004633393151,
          "below_floor_robot_geom_count": 0,
          "worst_below_floor_robot_geom": "",
          "floor_penetration_tolerance_m": 0.005,
          "locomotion_prior_goal_hold_scale": 1.0,
          "locomotion_prior_residual_stability_scale": 1.0,
          "reward_terms": {
            "alive": 1.0,
            "height_track": 0.4981280660375467,
            "velocity_track": 0.0022256841091768077,
            "yaw_track": 0.0,
            "contact_cadence": 0.0,
            "stance_contact": 0.0,
            "foot_clearance": 0.0,
            "no_support": -0.0,
            "double_support": -0.0,
            "foot_slip": -0.04009133204817772,
            "foot_spacing": -0.0,
            "self_collision": -0.0,
            "support_contract": -0.0,
            "upright": 0.9930725052579523,
            "movement_progress": 0.45502652672470184,
            "alternating_contact": 0.0,
            "no_progress": -3.2498979741357625,
            "gait_prior": 0.0,
            "action_rate": -8.135035168379545e-06,
            "energy": -3.012060932815075e-05,
            "residual_energy": -0.0003127333184238523,
            "residual_guard_suppression": -0.0,
            "residual_yaw_guard": -0.0,
            "residual_tilt_guard": -0.0,
            "tilt_margin": -0.0,
            "yaw_drift_margin": -0.13985700261812778,
            "drift": -0.0,
            "late_hold_instability": -0.0,
            "late_hold_speed": -0.0,
            "goal_hold_brake": -0.0,
            "goal_hold_slip": -0.0,
            "goal_hold_support": 0.0
          }
        },
        {
          "step": 27,
          "t_s": 0.54,
          "matched_task": "walk_forward",
          "reward": -0.44591044353570936,
          "done_reason": null,
          "tracked_delta_x": 0.10981490843486236,
          "tracked_delta_y": -0.032227320456201886,
          "tracked_z": 0.2519096797290819,
          "delta_yaw": -0.14654129614730008,
          "imu_pitch": 0.048351199011250325,
          "imu_roll": -0.11994299848298168,
          "left_foot_contact": false,
          "right_foot_contact": true,
          "foot_contact_switch_count": 1,
          "left_foot_slip_m_s": 0.0,
          "right_foot_slip_m_s": 0.04275951534509659,
          "max_foot_slip_m_s": 0.20772160589694977,
          "min_robot_geom_floor_clearance_m": -0.0007829786455692961,
          "below_floor_robot_geom_count": 0,
          "worst_below_floor_robot_geom": "",
          "floor_penetration_tolerance_m": 0.005,
          "locomotion_prior_goal_hold_scale": 1.0,
          "locomotion_prior_residual_stability_scale": 1.0,
          "reward_terms": {
            "alive": 1.0,
            "height_track": 0.49907841576789147,
            "velocity_track": 0.0014971991313969873,
            "yaw_track": 0.0,
            "contact_cadence": 0.0,
            "stance_contact": 0.0,
            "foot_clearance": 0.0,
            "no_support": -0.0,
            "double_support": -0.0,
            "foot_slip": -0.04275951534509659,
            "foot_spacing": -0.0,
            "self_collision": -0.0,
            "support_contract": -0.0,
            "upright": 0.9916551630196446,
            "movement_progress": 0.4758646032177369,
            "alternating_contact": 0.0,
            "no_progress": -3.1697515260856273,
            "gait_prior": 0.0,
            "action_rate": -9.19231039006263e-06,
            "energy": -3.4444943070411684e-05,
            "residual_energy": -0.0001291008957196027,
            "residual_guard_suppression": -0.0,
            "residual_yaw_guard": -0.0,
            "residual_tilt_guard": -0.0,
            "tilt_margin": -0.0,
            "yaw_drift_margin": -0.20132204509247537,
            "drift": -0.0,
            "late_hold_instability": -0.0,
            "late_hold_speed": -0.0,
            "goal_hold_brake": -0.0,
            "goal_hold_slip": -0.0,
            "goal_hold_support": 0.0
          }
        },
        {
          "step": 28,
          "t_s": 0.56,
          "matched_task": "walk_forward",
          "reward": -0.4160958245397343,
          "done_reason": null,
          "tracked_delta_x": 0.11493561264454988,
          "tracked_delta_y": -0.028883812680195936,
          "tracked_z": 0.2509755706920593,
          "delta_yaw": -0.17011783460226623,
          "imu_pitch": 0.06168098172785042,
          "imu_roll": -0.12738204871998798,
          "left_foot_contact": false,
          "right_foot_contact": true,
          "foot_contact_switch_count": 1,
          "left_foot_slip_m_s": 0.0,
          "right_foot_slip_m_s": 0.048878319561481476,
          "max_foot_slip_m_s": 0.20772160589694977,
          "min_robot_geom_floor_clearance_m": -0.0007634220036124087,
          "below_floor_robot_geom_count": 0,
          "worst_below_floor_robot_geom": "",
          "floor_penetration_tolerance_m": 0.005,
          "locomotion_prior_goal_hold_scale": 1.0,
          "locomotion_prior_residual_stability_scale": 1.0,
          "reward_terms": {
            "alive": 1.0,
            "height_track": 0.49979113529426233,
            "velocity_track": 0.0008193948525358518,
            "yaw_track": 0.0,
            "contact_cadence": 0.0,
            "stance_contact": 0.0,
            "foot_clearance": 0.0,
            "no_support": -0.0,
            "double_support": -0.0,
            "foot_slip": -0.048878319561481476,
            "foot_spacing": -0.0,
            "self_collision": -0.0,
            "support_contract": -0.0,
            "upright": 0.9900116101213627,
            "movement_progress": 0.49805432145971623,
            "alternating_contact": 0.0,
            "no_progress": -3.0844064559241686,
            "gait_prior": 0.0,
            "action_rate": -1.0201617842540144e-05,
            "energy": -4.138132557272911e-05,
            "residual_energy": -0.00012269987200852484,
            "residual_guard_suppression": -0.0,
            "residual_yaw_guard": -0.0,
            "residual_tilt_guard": -0.0,
            "tilt_margin": -0.0,
            "yaw_drift_margin": -0.27131322796653756,
            "drift": -0.0,
            "late_hold_instability": -0.0,
            "late_hold_speed": -0.0,
            "goal_hold_brake": -0.0,
            "goal_hold_slip": -0.0,
            "goal_hold_support": 0.0
          }
        },
        {
          "step": 29,
          "t_s": 0.58,
          "matched_task": "walk_forward",
          "reward": -0.3898128364200102,
          "done_reason": null,
          "tracked_delta_x": 0.12044832393321628,
          "tracked_delta_y": -0.02473918407923739,
          "tracked_z": 0.249799460542913,
          "delta_yaw": -0.19307498382909466,
          "imu_pitch": 0.07611111905286971,
          "imu_roll": -0.13497253533906092,
          "left_foot_contact": false,
          "right_foot_contact": true,
          "foot_contact_switch_count": 1,
          "left_foot_slip_m_s": 0.0,
          "right_foot_slip_m_s": 0.057634562253952026,
          "max_foot_slip_m_s": 0.20772160589694977,
          "min_robot_geom_floor_clearance_m": -0.00073597212436214,
          "below_floor_robot_geom_count": 0,
          "worst_below_floor_robot_geom": "",
          "floor_penetration_tolerance_m": 0.005,
          "locomotion_prior_goal_hold_scale": 1.0,
          "locomotion_prior_residual_stability_scale": 1.0,
          "reward_terms": {
            "alive": 1.0,
            "height_track": 0.4999682321880633,
            "velocity_track": 0.0003597411819033495,
            "yaw_track": 0.0,
            "contact_cadence": 0.0,
            "stance_contact": 0.0,
            "foot_clearance": 0.0,
            "no_support": -0.0,
            "double_support": -0.0,
            "foot_slip": -0.057634562253952026,
            "foot_spacing": -0.0,
            "self_collision": -0.0,
            "support_contract": -0.0,
            "upright": 0.988036304484937,
            "movement_progress": 0.5219427370439372,
            "alternating_contact": 0.0,
            "no_progress": -2.992527934446395,
            "gait_prior": 0.0,
            "action_rate": -1.0643870336934925e-05,
            "energy": -5.082373321056366e-05,
            "residual_energy": -0.0004151115717831999,
            "residual_guard_suppression": -0.0,
            "residual_yaw_guard": -0.0,
            "residual_tilt_guard": -0.0,
            "tilt_margin": -0.0,
            "yaw_drift_margin": -0.3494807754431734,
            "drift": -0.0,
            "late_hold_instability": -0.0,
            "late_hold_speed": -0.0,
            "goal_hold_brake": -0.0,
            "goal_hold_slip": -0.0,
            "goal_hold_support": 0.0
          }
        },
        {
          "step": 30,
          "t_s": 0.6,
          "matched_task": "walk_forward",
          "reward": -0.16980121037931642,
          "done_reason": null,
          "tracked_delta_x": 0.12631811570966958,
          "tracked_delta_y": -0.01977589721032731,
          "tracked_z": 0.248206177722701,
          "delta_yaw": -0.21665493209518438,
          "imu_pitch": 0.09496480004591033,
          "imu_roll": -0.14392088796635358,
          "left_foot_contact": false,
          "right_foot_contact": true,
          "foot_contact_switch_count": 1,
          "left_foot_slip_m_s": 0.0,
          "right_foot_slip_m_s": 0.061291906982660294,
          "max_foot_slip_m_s": 0.20772160589694977,
          "min_robot_geom_floor_clearance_m": -0.0007004570415498693,
          "below_floor_robot_geom_count": 0,
          "worst_below_floor_robot_geom": "",
          "floor_penetration_tolerance_m": 0.005,
          "locomotion_prior_goal_hold_scale": 1.0,
          "locomotion_prior_residual_stability_scale": 1.0,
          "reward_terms": {
            "alive": 1.0,
            "height_track": 0.49891050619342786,
            "velocity_track": 0.00029406646900158995,
            "yaw_track": 0.0,
            "contact_cadence": 0.0,
            "stance_contact": 0.0,
            "foot_clearance": 0.0,
            "no_support": -0.0,
            "double_support": -0.0,
            "foot_slip": -0.061291906982660294,
            "foot_spacing": -0.0,
            "self_collision": -0.0,
            "support_contract": -0.0,
            "upright": 0.9852020683406579,
            "movement_progress": 0.5017957425519508,
            "alternating_contact": 0.0,
            "no_progress": -2.6536430724205804,
            "gait_prior": 0.0,
            "action_rate": -7.866495288908482e-06,
            "energy": -5.2351802587509155e-05,
            "residual_energy": -0.0009518999722786248,
            "residual_guard_suppression": -0.0,
            "residual_yaw_guard": -0.0,
            "residual_tilt_guard": -0.0,
            "tilt_margin": -0.0,
            "yaw_drift_margin": -0.4400564962609589,
            "drift": -0.0,
            "late_hold_instability": -0.0,
            "late_hold_speed": -0.0,
            "goal_hold_brake": -0.0,
            "goal_hold_slip": -0.0,
            "goal_hold_support": 0.0
          }
        },
        {
          "step": 31,
          "t_s": 0.62,
          "matched_task": "walk_forward",
          "reward": 0.1089189447335305,
          "done_reason": null,
          "tracked_delta_x": 0.13254383249836715,
          "tracked_delta_y": -0.013984320304516738,
          "tracked_z": 0.24602110504902924,
          "delta_yaw": -0.24216262228829405,
          "imu_pitch": 0.11940167656829653,
          "imu_roll": -0.15613584559669927,
          "left_foot_contact": false,
          "right_foot_contact": true,
          "foot_contact_switch_count": 1,
          "left_foot_slip_m_s": 0.0,
          "right_foot_slip_m_s": 0.06499054282903671,
          "max_foot_slip_m_s": 0.20772160589694977,
          "min_robot_geom_floor_clearance_m": -0.0006535361169889425,
          "below_floor_robot_geom_count": 0,
          "worst_below_floor_robot_geom": "",
          "floor_penetration_tolerance_m": 0.005,
          "locomotion_prior_goal_hold_scale": 1.0,
          "locomotion_prior_residual_stability_scale": 0.9167253395240782,
          "reward_terms": {
            "alive": 1.0,
            "height_track": 0.4950446537703906,
            "velocity_track": 0.00025539683867078263,
            "yaw_track": 0.0,
            "contact_cadence": 0.0,
            "stance_contact": 0.0,
            "foot_clearance": 0.0,
            "no_support": -0.0,
            "double_support": -0.0,
            "foot_slip": -0.06499054282903671,
            "foot_spacing": -0.0,
            "self_collision": -0.0,
            "support_contract": -0.0,
            "upright": 0.9808022361902159,
            "movement_progress": 0.4532747039903738,
            "alternating_contact": 0.0,
            "no_progress": -2.2025701966758273,
            "gait_prior": 0.0,
            "action_rate": -7.89808400440961e-06,
            "energy": -5.518436431884766e-05,
            "residual_energy": -0.0017010305309668183,
            "residual_guard_suppression": -0.0013575470075011253,
            "residual_yaw_guard": -0.0,
            "residual_tilt_guard": -0.0,
            "tilt_margin": -0.0,
            "yaw_drift_margin": -0.5497756465644653,
            "drift": -0.0,
            "late_hold_instability": -0.0,
            "late_hold_speed": -0.0,
            "goal_hold_brake": -0.0,
            "goal_hold_slip": -0.0,
            "goal_hold_support": 0.0
          }
        },
        {
          "step": 32,
          "t_s": 0.64,
          "matched_task": "walk_forward",
          "reward": -8.253491105629083,
          "done_reason": null,
          "tracked_delta_x": 0.13919862936845284,
          "tracked_delta_y": -0.007397288720220329,
          "tracked_z": 0.24316401841480442,
          "delta_yaw": -0.269249451220043,
          "imu_pitch": 0.1496175733237347,
          "imu_roll": -0.17516781172151752,
          "left_foot_contact": true,
          "right_foot_contact": true,
          "foot_contact_switch_count": 1,
          "left_foot_slip_m_s": 0.6797677278518677,
          "right_foot_slip_m_s": 0.06644709408283234,
          "max_foot_slip_m_s": 0.6797677278518677,
          "min_robot_geom_floor_clearance_m": -0.0005191010476644983,
          "below_floor_robot_geom_count": 0,
          "worst_below_floor_robot_geom": "",
          "floor_penetration_tolerance_m": 0.005,
          "locomotion_prior_goal_hold_scale": 1.0,
          "locomotion_prior_residual_stability_scale": 0.7891868885585298,
          "reward_terms": {
            "alive": 1.0,
            "height_track": 0.48619579876154473,
            "velocity_track": 0.0,
            "yaw_track": 0.0,
            "contact_cadence": 0.0,
            "stance_contact": 0.0,
            "foot_clearance": 0.0,
            "no_support": -0.0,
            "double_support": -1.0,
            "foot_slip": -0.6797677278518677,
            "foot_spacing": -0.0,
            "self_collision": -0.0,
            "support_contract": -6.5953545570373535,
            "upright": 0.9736964217231004,
            "movement_progress": 0.0,
            "alternating_contact": 0.0,
            "no_progress": -1.7520722878870039,
            "gait_prior": 0.0,
            "action_rate": -7.5911806197837e-06,
            "energy": -6.018778309226036e-05,
            "residual_energy": -0.0022446378134191036,
            "residual_guard_suppression": -0.004233208601363003,
            "residual_yaw_guard": -0.0,
            "residual_tilt_guard": -0.0,
            "tilt_margin": -0.0,
            "yaw_drift_margin": -0.6796431279590093,
            "drift": -0.0,
            "late_hold_instability": -0.0,
            "late_hold_speed": -0.0,
            "goal_hold_brake": -0.0,
            "goal_hold_slip": -0.0,
            "goal_hold_support": 0.0
          }
        },
        {
          "step": 33,
          "t_s": 0.66,
          "matched_task": "walk_forward",
          "reward": -204.51948450553854,
          "done_reason": "support_contract",
          "tracked_delta_x": 0.14670032439548686,
          "tracked_delta_y": -0.0011824509797746371,
          "tracked_z": 0.2411353636533085,
          "delta_yaw": -0.2881464592525926,
          "imu_pitch": 0.1912752819412233,
          "imu_roll": -0.2169653186705503,
          "left_foot_contact": true,
          "right_foot_contact": false,
          "foot_contact_switch_count": 2,
          "left_foot_slip_m_s": 0.27564069628715515,
          "right_foot_slip_m_s": 0.0,
          "max_foot_slip_m_s": 0.6797677278518677,
          "min_robot_geom_floor_clearance_m": -0.0011854530404129052,
          "below_floor_robot_geom_count": 0,
          "worst_below_floor_robot_geom": "",
          "floor_penetration_tolerance_m": 0.005,
          "locomotion_prior_goal_hold_scale": 1.0,
          "locomotion_prior_residual_stability_scale": 0.653752743899785,
          "reward_terms": {
            "alive": 1.0,
            "height_track": 0.4778342977271593,
            "velocity_track": 0.0,
            "yaw_track": 0.0,
            "contact_cadence": 0.0,
            "stance_contact": 0.0,
            "foot_clearance": 0.0,
            "no_support": -0.0,
            "double_support": -0.0,
            "foot_slip": -0.27564069628715515,
            "foot_spacing": -0.0,
            "self_collision": -0.0,
            "support_contract": -6.5953545570373535,
            "upright": 0.9587453725751676,
            "movement_progress": 0.0,
            "alternating_contact": 0.0,
            "no_progress": -1.4289259593161463,
            "gait_prior": 0.0,
            "action_rate": -7.74493149947375e-06,
            "energy": -6.775977462530136e-05,
            "residual_energy": -0.001962109003216028,
            "residual_guard_suppression": -0.005617589922621846,
            "residual_yaw_guard": -1.0173044402132494e-05,
            "residual_tilt_guard": -0.0,
            "tilt_margin": -0.0,
            "yaw_drift_margin": -0.7783910810606811,
            "drift": -0.0,
            "late_hold_instability": -0.0,
            "late_hold_speed": -0.0,
            "goal_hold_brake": -0.0,
            "goal_hold_slip": -0.0,
            "goal_hold_support": 0.0,
            "support_contract_terminal_penalty": -100.0,
            "support_contract_after_progress": -39.12008650546316,
            "support_contract_remaining_horizon": -58.75
          }
        }
      ]
    }
  ],
  "success": {
    "slip_limit_m_s": 0.35,
    "required_alternating_contacts": 2,
    "fall_pitch_rad": 0.6,
    "fall_roll_rad": 0.6
  }
}
